PyYep/__init__.py
PyYep/exceptions.py
PyYep-1.5.1.dist-info/LICENSE
PyYep-1.5.1.dist-info/METADATA
PyYep-1.5.1.dist-info/WHEEL
PyYep-1.5.1.dist-info/top_level.txt
PyYep-1.5.1.dist-info/RECORD
