Metadata-Version: 2.1
Name: PyYep
Version: 1.5.1
Summary: A simple schema builder for value parsing and validation
Home-page: https://github.com/danielmbomfim/PyYep
Author: Daniel Montalvão Bomfim
Author-email: daniellsmv@hotmail.com
Project-URL: Bug Tracker, https://github.com/danielmbomfim/PyYep/issues
Classifier: Programming Language :: Python :: 3
Classifier: License :: OSI Approved :: MIT License
Classifier: Operating System :: OS Independent
Requires-Python: >=3.11
License-File: LICENSE
